bqmigratrr/__init__.py
bqmigratrr/commands/BigQuery.py
bqmigratrr/commands/__init__.py
bqmigratrr/commands/migrator.py
bqmigratrr/enums/DataType.py
bqmigratrr/enums/Mode.py
bqmigratrr/enums/__init__.py
bqmigratrr/models/Column.py
bqmigratrr/models/__init__.py
bqmigratrr-1.0.6.data/scripts/bqmigratrr
bqmigratrr-1.0.6.dist-info/LICENSE
bqmigratrr-1.0.6.dist-info/METADATA
bqmigratrr-1.0.6.dist-info/WHEEL
bqmigratrr-1.0.6.dist-info/top_level.txt
bqmigratrr-1.0.6.dist-info/version.txt
bqmigratrr-1.0.6.dist-info/version_full.txt
bqmigratrr-1.0.6.dist-info/RECORD
