Metadata-Version: 2.1
Name: bqmigratrr
Version: 1.0.6
Summary: Big query schema migration tool
Home-page: https://github.com/urbanmassage/bqmigratrr
Author: nick sharp
Author-email: nick.sharp@urban.co
License: UNKNOWN
Platform: UNKNOWN
Classifier: Programming Language :: Python :: 3
Classifier: License :: OSI Approved :: MIT License
Classifier: Operating System :: OS Independent
